LICENSE.txt
MANIFEST.in
README.md
setup.cfg
setup.py
InvoiceSpider/InvoiceSpider.pyd
InvoiceSpider/InvoiceSpiderExecuter.pyd
InvoiceSpider/__init__.py
InvoiceSpider.egg-info/PKG-INFO
InvoiceSpider.egg-info/SOURCES.txt
InvoiceSpider.egg-info/dependency_links.txt
InvoiceSpider.egg-info/top_level.txt
InvoiceSpider/package/__init__.py
InvoiceSpider/package/greenlet/__init__.py
InvoiceSpider/package/greenlet/_greenlet.cp38-win_amd64.pyd
InvoiceSpider/package/greenlet/greenlet.cpp
InvoiceSpider/package/greenlet/greenlet.h
InvoiceSpider/package/greenlet/greenlet_allocator.hpp
InvoiceSpider/package/greenlet/greenlet_compiler_compat.hpp
InvoiceSpider/package/greenlet/greenlet_cpython_compat.hpp
InvoiceSpider/package/greenlet/greenlet_exceptions.hpp
InvoiceSpider/package/greenlet/greenlet_greenlet.hpp
InvoiceSpider/package/greenlet/greenlet_internal.hpp
InvoiceSpider/package/greenlet/greenlet_refs.hpp
InvoiceSpider/package/greenlet/greenlet_slp_switch.hpp
InvoiceSpider/package/greenlet/greenlet_thread_state.hpp
InvoiceSpider/package/greenlet/greenlet_thread_state_dict_cleanup.hpp
InvoiceSpider/package/greenlet/greenlet_thread_support.hpp
InvoiceSpider/package/greenlet/slp_platformselect.h
InvoiceSpider/package/greenlet/platform/__init__.py
InvoiceSpider/package/greenlet/platform/setup_switch_x64_masm.cmd
InvoiceSpider/package/greenlet/platform/switch_aarch64_gcc.h
InvoiceSpider/package/greenlet/platform/switch_alpha_unix.h
InvoiceSpider/package/greenlet/platform/switch_amd64_unix.h
InvoiceSpider/package/greenlet/platform/switch_arm32_gcc.h
InvoiceSpider/package/greenlet/platform/switch_arm32_ios.h
InvoiceSpider/package/greenlet/platform/switch_arm64_masm.asm
InvoiceSpider/package/greenlet/platform/switch_arm64_masm.obj
InvoiceSpider/package/greenlet/platform/switch_arm64_msvc.h
InvoiceSpider/package/greenlet/platform/switch_csky_gcc.h
InvoiceSpider/package/greenlet/platform/switch_m68k_gcc.h
InvoiceSpider/package/greenlet/platform/switch_mips_unix.h
InvoiceSpider/package/greenlet/platform/switch_ppc64_aix.h
InvoiceSpider/package/greenlet/platform/switch_ppc64_linux.h
