Metadata-Version: 2.1
Name: InvoiceSpider
Version: 0.1.3
Summary: 国家税务总局全国增值税发票查询
Home-page: https://alidocs.dingtalk.com/i/p/4oJRz0VRJyvmLZMydy0mV7WvjQn7MG89
Author: renlingkun
Author-email: 17891967090@163.com
Classifier: Programming Language :: Python
Requires-Python: >=3.8
License-File: LICENSE.txt
